COPYING
ChangeLog
MANIFEST.in
README.rst
gns3-converter.py
setup.py
gns3_converter.egg-info/PKG-INFO
gns3_converter.egg-info/SOURCES.txt
gns3_converter.egg-info/dependency_links.txt
gns3_converter.egg-info/entry_points.txt
gns3_converter.egg-info/requires.txt
gns3_converter.egg-info/top_level.txt
gns3converter/__init__.py
gns3converter/adapters.py
gns3converter/configspec
gns3converter/converter.py
gns3converter/converterror.py
gns3converter/interfaces.py
gns3converter/main.py
gns3converter/models.py
gns3converter/node.py
gns3converter/topology.py
gns3converter/utils.py