Metadata-Version: 1.1
Name: gns3-converter
Version: 1.2.4
Summary: Convert old ini-style GNS3 topologies (<=0.8.7) to the newer version 1+ JSON format
Home-page: https://github.com/dlintott/gns3-converter
Author: Daniel Lintott
Author-email: daniel@serverb.co.uk
License: GPLv3+
Platform: any
Classifier: Development Status :: 5 - Production/Stable
Classifier: Environment :: Console
Classifier: Intended Audience :: Education
Classifier: Intended Audience :: Information Technology
Classifier: License :: OSI Approved :: GNU General Public License v3 or later (GPLv3+)
Classifier: Natural Language :: English
Classifier: Operating System :: OS Independent
Classifier: Programming Language :: Python :: 3
Classifier: Programming Language :: Python :: 3.3
Classifier: Programming Language :: Python :: 3.4
Classifier: Topic :: Education
Classifier: Topic :: Utilities
